[{"name": "GitDownloads", "type": "directory", "children": [{"name": "LICENSE", "type": "file"}, {"name": "Diagrams", "type": "directory", "children": [{"name": "treediagram.png", "type": "file"}, {"name": "MathNodesUml.png", "type": "file"}]}, {"name": "README.md", "type": "file"}, {"name": ".gitignore", "type": "file"}, {"name": "src", "type": "directory", "children": [{"name": "mathNode", "type": "directory", "children": [{"name": "Mult.java", "type": "file"}, {"name": "Operator.java", "type": "file"}, {"name": "Add.java", "type": "file"}, {"name": "Int.java", "type": "file"}, {"name": "Pow.java", "type": "file"}, {"name": "Factory.java", "type": "file"}, {"name": "Div.java", "type": "file"}, {"name": "Expression.java", "type": "file"}, {"name": "Dec.java", "type": "file"}, {"name": "Sub.java", "type": "file"}]}, {"name": "test", "type": "directory", "children": [{"name": "MathTreeTest.java", "type": "file"}, {"name": "MathNodeTest.java", "type": "file"}, {"name": "StringScannerTest.java", "type": "file"}]}, {"name": "mathTree", "type": "directory", "children": [{"name": "StringScanner.java", "type": "file"}, {"name": "CalcApp.java", "type": "file"}, {"name": "MathTree.java", "type": "file"}]}]}]}]